job_defense_shield/__init__.py
job_defense_shield/base.py
job_defense_shield/cleaner.py
job_defense_shield/efficiency.py
job_defense_shield/email_translator.py
job_defense_shield/greeting.py
job_defense_shield/job_defense_shield.py
job_defense_shield/ldap_lookups.py
job_defense_shield/raw_job_data.py
job_defense_shield/utils.py
job_defense_shield/workday.py
job_defense_shield/alert/__init__.py
job_defense_shield/alert/cancel_zero_gpu_jobs.py
job_defense_shield/alert/compute_efficiency.py
job_defense_shield/alert/excess_cpu_memory.py
job_defense_shield/alert/excessive_time_limits.py
job_defense_shield/alert/gpu_model_too_powerful.py
job_defense_shield/alert/jobs_overview.py
job_defense_shield/alert/longest_queued.py
job_defense_shield/alert/most_cores.py
job_defense_shield/alert/most_gpus.py
job_defense_shield/alert/multinode_cpu_fragmentation.py
job_defense_shield/alert/multinode_gpu_fragmentation.py
job_defense_shield/alert/serial_allocating_multiple_cores.py
job_defense_shield/alert/too_many_cores_per_gpu.py
job_defense_shield/alert/too_much_cpu_mem_per_gpu.py
job_defense_shield/alert/usage_by_slurm_account.py
job_defense_shield/alert/usage_overview.py
job_defense_shield/alert/zero_cpu_utilization.py
job_defense_shield/alert/zero_util_gpu_hours.py
job_defense_shield-1.2.5.dist-info/METADATA
job_defense_shield-1.2.5.dist-info/WHEEL
job_defense_shield-1.2.5.dist-info/entry_points.txt
job_defense_shield-1.2.5.dist-info/licenses/LICENSE
job_defense_shield-1.2.5.dist-info/RECORD
