Metadata-Version: 2.4
Name: job-defense-shield
Version: 1.2.5
Summary: Identify and reduce instances of underutilization by the users of high-performance computing systems
Project-URL: Documentation, https://princetonuniversity.github.io/job_defense_shield
Project-URL: Repository, https://github.com/PrincetonUniversity/job_defense_shield
Author-email: Jonathan Halverson <halverson@princeton.edu>
License:                     GNU GENERAL PUBLIC LICENSE
License-File: LICENSE
Keywords: HPC,Jobstats,Slurm,alert,monitoring,underutilization
Classifier: Development Status :: 5 - Production/Stable
Classifier: Environment :: Console
Classifier: Intended Audience :: Information Technology
Classifier: Intended Audience :: System Administrators
Classifier: License :: OSI Approved :: GNU General Public License v2 (GPLv2)
Classifier: Operating System :: OS Independent
Classifier: Programming Language :: Python
Classifier: Programming Language :: Python :: 3
Classifier: Programming Language :: Python :: 3.7
Classifier: Programming Language :: Python :: 3.8
Classifier: Programming Language :: Python :: 3.9
Classifier: Programming Language :: Python :: 3.10
Classifier: Programming Language :: Python :: 3.11
Classifier: Programming Language :: Python :: 3.12
Classifier: Topic :: System :: Monitoring
Classifier: Typing :: Typed
Requires-Python: >=3.7
Requires-Dist: pandas>=2.1.0
Requires-Dist: pyarrow>=15.0.0
Requires-Dist: pyyaml>=6.0
Requires-Dist: requests>=2.31.0
Provides-Extra: check
Requires-Dist: ruff>=0.6.0; extra == 'check'
Provides-Extra: test
Requires-Dist: pytest>=7; extra == 'test'
